pystein/__init__.py
pystein/constants.py
pystein/coords.py
pystein/curvature.py
pystein/geodesic.py
pystein/gravity.py
pystein/matter.py
pystein/metric.py
pystein/symbols.py
pystein/tensor.py
pystein/utilities.py
pystein/tests/__init__.py
pystein/tests/test_constants.py
pystein/tests/test_coords.py
pystein/tests/test_curvature.py
pystein/tests/test_geodesic.py
pystein/tests/test_gravity.py
pystein/tests/test_matter.py
pystein/tests/test_metric.py
pystein/tests/test_pynstein.py
pystein/tests/test_symbols.py
pystein/tests/test_utilities.py
pystein-0.5.3.dist-info/LICENSE
pystein-0.5.3.dist-info/METADATA
pystein-0.5.3.dist-info/WHEEL
pystein-0.5.3.dist-info/top_level.txt
pystein-0.5.3.dist-info/RECORD
