Metadata-Version: 2.1
Name: pystein
Version: 0.5.3
Summary: Collapse
Home-page: https://github.com/JWKennington/pystein
Author: James Kennington
Author-email: jwkennington@psu.edu
License: MIT
Platform: UNKNOWN
Classifier: Programming Language :: Python
Classifier: Programming Language :: Python :: 3.7
Classifier: Programming Language :: Python :: 3.8
Classifier: Operating System :: MacOS
Classifier: Operating System :: POSIX :: Linux
Requires-Python: >=3.7
Requires-Dist: matplotlib
Requires-Dist: numpy
Requires-Dist: palettable
Requires-Dist: pytest
Requires-Dist: scipy
Requires-Dist: simpy
